ragflow_mcp_server_v0_2_0/__init__.py
ragflow_mcp_server_v0_2_0/config.py
ragflow_mcp_server_v0_2_0/server.py
ragflow_mcp_server_v0_2_0-0.2.0.dist-info/METADATA
ragflow_mcp_server_v0_2_0-0.2.0.dist-info/WHEEL
ragflow_mcp_server_v0_2_0-0.2.0.dist-info/entry_points.txt
ragflow_mcp_server_v0_2_0-0.2.0.dist-info/RECORD
