Metadata-Version: 2.4
Name: ragflow-mcp-server-v0-2-0
Version: 0.2.0
Summary: RAGFlow MCP Server V0.2.0
Requires-Python: >=3.10
Requires-Dist: mcp>=1.12.2
